py_temporal_doc/__init__.py
py_temporal_doc/base_types/__init__.py
py_temporal_doc/base_types/cls/__init__.py
py_temporal_doc/base_types/cls/parser.py
py_temporal_doc/base_types/data/__init__.py
py_temporal_doc/commands/__init__.py
py_temporal_doc/commands/command.py
py_temporal_doc/commands/command_list.py
py_temporal_doc/commands/consts.py
py_temporal_doc/commands/container.py
py_temporal_doc/commands/generate_json/__init__.py
py_temporal_doc/commands/generate_json/core.py
py_temporal_doc/generator/__init__.py
py_temporal_doc/generator/consts.py
py_temporal_doc/generator/container.py
py_temporal_doc/generator/model/__init__.py
py_temporal_doc/generator/model/response.py
py_temporal_doc/generator/model/temporal_activity.py
py_temporal_doc/generator/model/workflow.py
py_temporal_doc/generator/model/workflow_caller.py
py_temporal_doc/generator/model/workflow_schedule.py
py_temporal_doc/generator/parser.py
py_temporal_doc/generator/processor/__init__.py
py_temporal_doc/generator/processor/base_processor.py
py_temporal_doc/generator/processor/doc_workflow_caller_processor.py
py_temporal_doc/generator/processor/doc_workflow_schedule_processor.py
py_temporal_doc/generator/processor/doc_workflow_sequence_processor.py
py_temporal_doc/generator/processor/temporal_activity_processor.py
py_temporal_doc/generator/processor/temporal_workflow_processor.py
py_temporal_doc/main.py
py_temporal_doc/module/__init__.py
py_temporal_doc/module/document.py
py_temporal_doc-0.0.2.dist-info/LICENSE
py_temporal_doc-0.0.2.dist-info/METADATA
py_temporal_doc-0.0.2.dist-info/WHEEL
py_temporal_doc-0.0.2.dist-info/entry_points.txt
py_temporal_doc-0.0.2.dist-info/RECORD
