Metadata-Version: 2.1
Name: py-temporal-doc
Version: 0.0.2
Summary: Temporal documentation decorator plugin for python
License: Apache
Author: Reecenil Valencia
Author-email: reecenil.h.valencia@gmail.com
Requires-Python: >=3.11,<4.0
Classifier: License :: Other/Proprietary License
Classifier: Programming Language :: Python :: 3
Classifier: Programming Language :: Python :: 3.11
Requires-Dist: click (>=8.1.7,<9.0.0)
Requires-Dist: dependency-injector (>=4.41.0,<5.0.0)
Requires-Dist: pydantic (>=1.10.2,<2.0.0)
